noor_aftab/__init__.py
noor_aftab/__main__.py
noor_aftab/print_me_funcs.py
noor_aftab-0.1.0.dist-info/METADATA
noor_aftab-0.1.0.dist-info/WHEEL
noor_aftab-0.1.0.dist-info/entry_points.txt
noor_aftab-0.1.0.dist-info/top_level.txt
noor_aftab-0.1.0.dist-info/RECORD
