Metadata-Version: 2.4
Name: noor_aftab
Version: 0.1.0
Summary: My first package!
Author-email: Noor_Aftab <noor.aftab@gmail.com>
Maintainer-email: Noor_Aftab <noor.aftab@gmail.comm>
Project-URL: Homepage, https://github.com/aftabn81
Project-URL: Documentation, https://github.com/aftabn81/README.md
Keywords: Aftab
Classifier: Programming Language :: Python :: 3.9
Classifier: Programming Language :: Python :: Implementation :: CPython
Classifier: License :: OSI Approved :: BSD License
Classifier: Intended Audience :: Developers
Classifier: Operating System :: POSIX :: Linux
Classifier: Operating System :: Microsoft :: Windows
Classifier: Operating System :: MacOS
Classifier: Operating System :: MacOS :: MacOS X
Requires-Python: >=3.9
